{
  "root": "dist",
  "clean_urls": true,
  "routes": {
    "/**": "index.html"
  },
  "headers": {
    "/**": {
      "Strict-Transport-Security": "max-age=31536000; includeSubDomains",
      "X-Content-Type-Options": "nosniff",
      "X-Frame-Options": "DENY",
      "X-XSS-Protection": "1; mode=block",
      "Content-Security-Policy": "default-src 'self'; script-src 'self' 'unsafe-inline' 'unsafe-eval'; style-src 'self' 'unsafe-inline'; img-src 'self' data: https:; font-src 'self' https:; connect-src 'self' https:;"
    }
  },
  "https_only": true,
  "error_page": "index.html"
} 